pmmoto/__init__.py
pmmoto/filters/equilibrium_distribution.py
pmmoto/filters/connected_components.py
pmmoto/filters/__init__.py
pmmoto/filters/morphological_operators.py
pmmoto/filters/porosimetry.py
pmmoto/filters/distance/_distance.pyx
pmmoto/filters/distance/_distance.hpp
pmmoto/filters/distance/threadpool.h
pmmoto/filters/distance/__init__.py
pmmoto/filters/distance/_distance.pyi
pmmoto/filters/distance/_distance.cpython-311-darwin.so
pmmoto/filters/distance/euclidean_distance_transform.py
pmmoto/filters/distance/_distance.cpp
pmmoto/filters/distance/_distance.pxd
pmmoto/core/pmmoto.py
pmmoto/core/domain_discretization.py
pmmoto/core/logging.py
pmmoto/core/boundary_types.py
pmmoto/core/domain_decompose.py
pmmoto/core/orientation.py
pmmoto/core/domain.py
pmmoto/core/_voxels.pyi
pmmoto/core/_voxels.pxd
pmmoto/core/_voxels.cpp
pmmoto/core/__init__.py
pmmoto/core/subdomain.py
pmmoto/core/features.py
pmmoto/core/subdomain_padded.py
pmmoto/core/_voxels.hpp
pmmoto/core/utils.py
pmmoto/core/communication.py
pmmoto/core/_voxels.pyx
pmmoto/core/voxels.py
pmmoto/core/subdomain_features.py
pmmoto/core/subdomain_verlet.py
pmmoto/core/_voxels.cpython-311-darwin.so
pmmoto/analysis/_minkowski.pyi
pmmoto/analysis/bins.pxd
pmmoto/analysis/minkowskic.h
pmmoto/analysis/_bins.cpython-311-darwin.so
pmmoto/analysis/quantimpyc.h
pmmoto/analysis/_bins.pyi
pmmoto/analysis/_bins.cpp
pmmoto/analysis/__init__.py
pmmoto/analysis/_minkowski.pyx
pmmoto/analysis/stats.py
pmmoto/analysis/quantimpyc.c
pmmoto/analysis/_bins.pyx
pmmoto/analysis/minkowskic.c
pmmoto/analysis/minkowski.py
pmmoto/analysis/average.py
pmmoto/analysis/_minkowski.cpython-311-darwin.so
pmmoto/analysis/_minkowski.c
pmmoto/analysis/bins.py
pmmoto/analysis/bins.hpp
pmmoto/io/_data_read.cpython-311-darwin.so
pmmoto/io/_data_read.cpp
pmmoto/io/_data_read.pxd
pmmoto/io/_data_read.pyi
pmmoto/io/__init__.py
pmmoto/io/_dataOutput.pyx
pmmoto/io/data_read.hpp
pmmoto-1.0.7.dist-info/RECORD
pmmoto-1.0.7.dist-info/WHEEL
pmmoto-1.0.7.dist-info/top_level.txt
pmmoto-1.0.7.dist-info/METADATA
pmmoto-1.0.7.dist-info/licenses/LICENSE
