Metadata-Version: 2.4
Name: pmmoto
Version: 1.0.7
Summary: Porous Media Topology and Morphology Toolkit
Author-email: "Timothy M. Weigand" <timothy.weigand@unc.edu>
License: MIT
Project-URL: Homepage, https://tmweigand.github.io/PMMoTo/
Project-URL: Source, https://github.com/tmweigand/PMMoTo
Project-URL: Issue Tracker, https://github.com/tmweigand/PMMoTo/issues
Classifier: Programming Language :: Python :: 3.10
Classifier: Programming Language :: Python :: 3.11
Classifier: Programming Language :: Python :: 3.12
Classifier: Programming Language :: Python :: 3.13
Requires-Python: >=3.10
License-File: LICENSE
Requires-Dist: numpy>=2.0
Requires-Dist: mpi4py>=4.0.0
Requires-Dist: scipy>=1.11
Requires-Dist: connected_components_3d>=3.12.4
Requires-Dist: matplotlib>=3.0
Requires-Dist: typing_extensions>=4.6
Provides-Extra: dev
Requires-Dist: pytest>=6.0; extra == "dev"
Requires-Dist: pytest-cov>=2.0; extra == "dev"
Requires-Dist: mypy>=1.15; extra == "dev"
Requires-Dist: tox>=3.24; extra == "dev"
Requires-Dist: pytest_benchmark>=5.1.0; extra == "dev"
Requires-Dist: ruff>=0.11.5; extra == "dev"
Requires-Dist: interrogate>=1.5.0; extra == "dev"
Requires-Dist: edt>=3.1.0; extra == "dev"
Requires-Dist: pytest-mpi-tmweigand==0.7.0; extra == "dev"
Provides-Extra: docs
Requires-Dist: sphinx>=7.0; extra == "docs"
Requires-Dist: sphinx_rtd_theme; extra == "docs"
Requires-Dist: myst-parser; extra == "docs"
Requires-Dist: sphinxcontrib-bibtex; extra == "docs"
Requires-Dist: typing_extensions; extra == "docs"
Dynamic: license-file
